newsfeed/__init__.py
newsfeed/news/__init__.py
newsfeed/news/apis/__init__.py
newsfeed/news/apis/filters.py
newsfeed/news/apis/query.py
newsfeed/news/db/__init__.py
newsfeed/news/db/events.py
newsfeed/news/db/gkg.py
newsfeed/news/db/others.py
newsfeed/utils/CAMEO.py
newsfeed/utils/__init__.py
newsfeed/utils/fulltext.py
newsfeed-0.1.5.dist-info/licenses/LICENSE
newsfeed-0.1.5.dist-info/METADATA
newsfeed-0.1.5.dist-info/WHEEL
newsfeed-0.1.5.dist-info/top_level.txt
newsfeed-0.1.5.dist-info/RECORD
