Metadata-Version: 2.4
Name: newsfeed
Version: 0.1.5
Home-page: https://github.com/Cyclododecene/newsfeed
Author: Cyclododecene
Author-email: terenceliu1012@outlook.com
License: MIT
Keywords: GDELT NewsFeed
Classifier: Programming Language :: Python :: 3.11
Classifier: Programming Language :: Python :: 3.12
Classifier: License :: OSI Approved :: MIT License
Classifier: Operating System :: OS Independent
Requires-Python: >=3.9
License-File: LICENSE
Requires-Dist: numpy>=2.4.0
Requires-Dist: pandas>=2.3.3
Requires-Dist: requests>=2.22.0
Requires-Dist: tqdm>=4.67.1
Requires-Dist: newspaper3k>=0.2.8
Requires-Dist: lxml>=4.4.2
Requires-Dist: lxml-html-clean>=0.4.3
Requires-Dist: beautifulsoup4>=4.14.3
Requires-Dist: fake-useragent>=2.2.0
Requires-Dist: nltk>=3.9.2
Dynamic: author
Dynamic: author-email
Dynamic: classifier
Dynamic: description
Dynamic: description-content-type
Dynamic: home-page
Dynamic: keywords
Dynamic: license
Dynamic: license-file
Dynamic: requires-dist
Dynamic: requires-python
